Doc/__init__.py
Doc/getBitMEXData_help.txt
getBitMEXData/__init__.py
getBitMEXData/auth.py
getBitMEXData/getBitMEXData.py
getBitMEXData/getBitMEXtypes.py
getBitMEXData/settings.py
getBitMEXData/update_kola.py
getBitMEXData/utils.py
getBitMEXData-0.1.3.dist-info/LICENSE.txt
getBitMEXData-0.1.3.dist-info/METADATA
getBitMEXData-0.1.3.dist-info/WHEEL
getBitMEXData-0.1.3.dist-info/entry_points.txt
getBitMEXData-0.1.3.dist-info/top_level.txt
getBitMEXData-0.1.3.dist-info/RECORD
